syft_crypto_python-0.1.2b2.dist-info/METADATA
syft_crypto_python-0.1.2b2.dist-info/WHEEL
syft_crypto_python/__init__.py
syft_crypto_python/_native.abi3.so
syft_crypto_python-0.1.2b2.dist-info/RECORD
