Metadata-Version: 2.4
Name: syft-crypto-python
Version: 0.1.2b2
Classifier: Programming Language :: Rust
Classifier: Programming Language :: Python
Classifier: Programming Language :: Python :: 3
Classifier: Programming Language :: Python :: 3 :: Only
Classifier: License :: OSI Approved :: Apache Software License
Classifier: Operating System :: OS Independent
Summary: Python bindings for the Syft crypto protocol
Author: OpenMined
License: Apache-2.0
Requires-Python: >=3.9
Project-URL: Homepage, https://github.com/OpenMined/syft-crypto-core
Project-URL: Repository, https://github.com/OpenMined/syft-crypto-core
